darklib/DarkTools.py
darklib/__init__.py
darklib-0.1.0.dist-info/METADATA
darklib-0.1.0.dist-info/WHEEL
darklib-0.1.0.dist-info/top_level.txt
darklib-0.1.0.dist-info/RECORD
