Metadata-Version: 2.1
Name: darklib
Version: 0.1.0
Summary: • Script Very Nice To Helping Programmer .
Home-page: 
Author: Dark Tools
Author-email: mikomiko11332244@gmail.com
Project-URL: Bug Tracker, https://github.com/pypa/sampleproject/issues
Classifier: Programming Language :: Python :: 3
Classifier: License :: OSI Approved :: MIT License
Classifier: Operating System :: OS Independent
Requires-Python: >=3.9
